flask_get_ip/__init__.py
flask_get_ip-5.0.dist-info/METADATA
flask_get_ip-5.0.dist-info/WHEEL
flask_get_ip-5.0.dist-info/top_level.txt
flask_get_ip-5.0.dist-info/RECORD
